agentkit/__init__.py
agentkit/version.py
agentkit/apps/__init__.py
agentkit/apps/base_app.py
agentkit/apps/utils.py
agentkit/apps/a2a_app/__init__.py
agentkit/apps/a2a_app/a2a_app.py
agentkit/apps/a2a_app/telemetry.py
agentkit/apps/agent_server_app/__init__.py
agentkit/apps/agent_server_app/agent_server_app.py
agentkit/apps/agent_server_app/middleware.py
agentkit/apps/agent_server_app/telemetry.py
agentkit/apps/mcp_app/__init__.py
agentkit/apps/mcp_app/mcp_app.py
agentkit/apps/mcp_app/telemetry.py
agentkit/apps/simple_app/__init__.py
agentkit/apps/simple_app/simple_app.py
agentkit/apps/simple_app/simple_app_handlers.py
agentkit/apps/simple_app/telemetry.py
agentkit/client/__init__.py
agentkit/client/base_agentkit_client.py
agentkit/client/base_iam_client.py
agentkit/client/base_service_client.py
agentkit/platform/__init__.py
agentkit/platform/configuration.py
agentkit/platform/constants.py
agentkit/sdk/__init__.py
agentkit/sdk/account/client.py
agentkit/sdk/account/types.py
agentkit/sdk/identity/__init__.py
agentkit/sdk/identity/auth.py
agentkit/sdk/knowledge/__init__.py
agentkit/sdk/knowledge/client.py
agentkit/sdk/knowledge/types.py
agentkit/sdk/mcp/__init__.py
agentkit/sdk/mcp/client.py
agentkit/sdk/mcp/types.py
agentkit/sdk/memory/__init__.py
agentkit/sdk/memory/client.py
agentkit/sdk/memory/types.py
agentkit/sdk/runtime/__init__.py
agentkit/sdk/runtime/client.py
agentkit/sdk/runtime/types.py
agentkit/sdk/tools/__init__.py
agentkit/sdk/tools/client.py
agentkit/sdk/tools/types.py
agentkit/toolkit/__init__.py
agentkit/toolkit/context.py
agentkit/toolkit/errors.py
agentkit/toolkit/models.py
agentkit/toolkit/reporter.py
agentkit/toolkit/builders/__init__.py
agentkit/toolkit/builders/base.py
agentkit/toolkit/builders/local_docker.py
agentkit/toolkit/builders/ve_pipeline.py
agentkit/toolkit/cli/__init__.py
agentkit/toolkit/cli/__main__.py
agentkit/toolkit/cli/cli.py
agentkit/toolkit/cli/cli_build.py
agentkit/toolkit/cli/cli_config.py
agentkit_sdk_python-0.4.3.dist-info/licenses/LICENSE
agentkit_sdk_python-0.4.3.dist-info/METADATA
agentkit_sdk_python-0.4.3.dist-info/WHEEL
agentkit_sdk_python-0.4.3.dist-info/entry_points.txt
agentkit_sdk_python-0.4.3.dist-info/top_level.txt
agentkit_sdk_python-0.4.3.dist-info/RECORD
