Metadata-Version: 2.4
Name: agentkit-sdk-python
Version: 0.4.3
Summary: Python SDK for transforming any AI agent into a production-ready application. Framework-agnostic primitives for runtime, memory, authentication, and tools with volcengine-managed infrastructure.
Author-email: Xiangrui Cheng <innsdcc@gmail.com>, Yumeng Bao <baoyumeng.123@gmail.com>, Yaozheng Fang <fangyozheng@gmail.com>, Guodong Li <cu.eric.lee@gmail.com>
License:                                  Apache License
Classifier: Development Status :: 4 - Beta
Classifier: Intended Audience :: Developers
Classifier: License :: OSI Approved :: Apache Software License
Classifier: Programming Language :: Python :: 3
Classifier: Programming Language :: Python :: 3.10
Classifier: Programming Language :: Python :: 3.11
Classifier: Programming Language :: Python :: 3.12
Classifier: Topic :: Scientific/Engineering :: Artificial Intelligence
Classifier: Topic :: Software Development :: Libraries :: Python Modules
Requires-Python: >=3.10
License-File: LICENSE
Requires-Dist: a2a-sdk>=0.3.7
Requires-Dist: fastapi>=0.117.1
Requires-Dist: fastmcp>=2.12.3
Requires-Dist: opentelemetry-api<=1.37.0,>=1.32.1
Requires-Dist: opentelemetry-exporter-otlp-proto-common<=1.37.0,>=1.32.1
Requires-Dist: opentelemetry-exporter-otlp-proto-grpc<=1.37.0,>=1.32.1
Requires-Dist: opentelemetry-sdk<=1.37.0,>=1.32.1
Requires-Dist: pydantic>=2.11.9
Requires-Dist: requests>=2.32.5
Requires-Dist: uvicorn>=0.37.0
Requires-Dist: pyyaml
Requires-Dist: python-dotenv>=1.1.0
Requires-Dist: prompt_toolkit
Requires-Dist: typer
Requires-Dist: rich
Requires-Dist: docker
Requires-Dist: jinja2
Requires-Dist: tos>=2.8.7
Requires-Dist: volcengine
Requires-Dist: pyfiglet>=1.0.2
Requires-Dist: typing_extensions>=4.12
Requires-Dist: pyreadline3; sys_platform == "win32"
Provides-Extra: extensions
Provides-Extra: toolkit
Provides-Extra: dev
Dynamic: license-file
